Workbook

Sheet 00_Cover
B2: V A L E N C E
B3: VALENCE VALUATION PLATFORM
B5: OIL & NATURAL GAS CORPORATION LIMITED
B6: Ticker: ONGC | Market: INDIA | Fiscal Basis: March 31
B7: MODEL METADATA
B8: Company Name | C8: Oil & Natural Gas Corporation Limited
B9: Ticker Symbol | C9: ONGC
B10: Primary Market | C10: INDIA
B11: Reporting Currency | C11: INR
B12: Display Units | C12: crores
B13: Model Specification Version | C13: 1.0.0
B14: Model Generation Date | C14: 2026-08-19
B15: Historical Periods | C15: FY24, FY25, FY26
B16: Forecast Periods | C16: FY27, FY28, FY29, FY30, FY31
B17: Scenarios Modeled | C17: base, bull, bear
B20: By Sourabh

Sheet 01_Model_Guide
B2: WORKBOOK MODEL GUIDE
B3: Complete Tab Architecture and Navigation Reference
B5: Group | C5: Tab Name | D5: Description
B6: Front Matter | C6: 00_Cover | D6: Company cover page, metadata, and branding slot
B7: Front Matter | C7: 01_Model_Guide | D7: Workbook structure and tab navigation reference
B8: Front Matter | C8: 02_Executive_Summary | D8: 60-second valuation overview & scenario outputs
B9: Front Matter | C9: 03_Model_Control | D9: Scenario selector and global model controls
B10: Historical Financials | C10: 10_Income_Statement | D10: Historical Income Statement (FY24-FY26)
B11: Historical Financials | C11: 11_Balance_Sheet | D11: Historical Balance Sheet (FY24-FY26)
B12: Historical Financials | C12: 12_Cash_Flow | D12: Historical Cash Flow Statement (FY24-FY26)
B13: Historical Financials | C13: 13_Financial_Ratios | D13: Historical margins, growth rates & working capital
B14: Historical Financials | C14: 14_Historical_Drivers | D14: Historical financial driver series
B15: Forecast & Schedules | C15: 20_Operating_Model | D15: Combined 3-statement forecast model (FY27-FY31)
B16: Forecast & Schedules | C16: 21_Revenue_Build | D16: Segment revenue forecast & YoY growth
... B32: QA / Documentation | C32: 53_Methodology | D32: System derivation and valuation methodology notes
B35: HOW TO USE THIS MODEL (STUDENT & ANALYST GUIDE)
B36: A beginner-friendly step-by-step guide to reading, modifying, and understanding this financial model.
B38: 1. VALUATION CONCEPTUAL OVERVIEW (WHAT IS A DCF?)
B39: Core Objective | C39: Calculate the intrinsic fair value per share of a company by discounting its future cash flow generator back to today.
B40: Step 1: Cash Flow | C40: Forecast 5 years of Free Cash Flow to Firm (FCFF) — the net cash left over after operating expenses, taxes, and capital investments.
B41: Step 2: Discount Rate | C41: Discount future cash flows back to present value using WACC (Weighted Average Cost of Capital) to adjust for risk and time value of money.
B42: Step 3: Equity Bridge | C42: Add Cash & Investments to Enterprise Value, subtract Total Debt to find Equity Value, and divide by Diluted Share Count.
B43: Step 4: Decision Rule | C43: If Implied Fair Price > Live Market Price, the stock is Undervalued (Bullish). If lower, the stock is Overvalued (Bearish).
B45: Convention | C45: Cell Type | D45: Description & How to Interact
B46: Blue Text / Shaded Fill | C46: Analyst Input / Override | D46: EDITABLE BY YOU! Modify these numbers (e.g. expected revenue growth % or profit margins) in 03_Model_Control or 51_Assumption_Log.
B47: Black Text | C47: Dynamic Excel Formula | D47: AUTOMATED MATH! Calculated automatically using standard accounting, 3-statement, and DCF formulas.
B48: Blue Underline | C48: Hyperlink Navigation | D48: CLICKABLE LINKS! Click any tab name to navigate directly to that worksheet.
B49: Green / Red Text | C49: QA / Delta Indicator | D49: MODEL FEEDBACK! Green indicates balance sheet 100% balance or positive upside; Red flags potential errors or downside.
B51: Workflow Step | C51: Target Sheet | D51: Modeling Action & Purpose
B52: Step 1: Executive Overview | C52: 02_Executive_Summary | D52: Start here! Get a 60-second summary of implied share price vs market benchmark, WACC, and scenario outputs.
B53: Step 2: Operating Model | C53: 20_Operating_Model | D53: Inspect historical financial actuals (FY24-FY26) and 5-year integrated 3-statement forecast (FY27-FY31).
B54: Step 3: WACC & DCF Schedule | C54: 30_WACC & 31_DCF | D54: Examine CAPM Cost of Equity, mid-year discount factors (1+WACC)^-(t-0.5), free cash flows, and non-operating equity bridge.
B55: Step 4: Terminal Value & ROIC | C55: 32_Terminal_Value | D55: Validate dual terminal value outputs (Gordon Growth vs Exit Multiple) and check implied terminal ROIC consistency.
B56: Step 5: Sensitivity & Reverse DCF | C56: 33_Sensitivity & 34_Reverse_DCF | D56: Test 2D sensitivity matrices (WACC x Growth, WACC x Multiple) and solve for market-implied growth expectations.
B57: Step 6: Scenario & Audit Log | C57: 35_Scenario_Analysis & 52_Model_Checks | D57: Compare Base, Bull, and Bear cases side-by-side and review automated QA check results.
... B64: Implied Share Price | C64: Equity Value / Diluted Shares | D64: Calculates the fair value price per share to compare directly against live market stock price.

Sheet 02_Executive_Summary
B2: OIL & NATURAL GAS CORPORATION LIMITED (ONGC)
B3: EXECUTIVE VALUATION SUMMARY (60-SECOND OVERVIEW)
B5: Market Benchmark Price | C5: Base Implied Price | D5: Implied Upside / (Downside) | E5: WACC % | F5: QA Status
B6: 235.35 | C6: ='35_Scenario_Analysis'!C6 -> 384.52 | D6: =IF(B6=0,"N/A",(C6-B6)/B6) -> 0.63382197 | E6: ='30_WACC'!C15 -> 0.105567 | F6: MODEL VALID
B9: Valuation Metric | C9: Base Scenario | D9: Bull Scenario | E9: Bear Scenario
B10: Implied Share Price (INR) | C10: ='35_Scenario_Analysis'!C6 -> 384.52 | D10: ='35_Scenario_Analysis'!D6 -> 633.94 | E10: ='35_Scenario_Analysis'!E6 -> 206.99
B11: Enterprise Value (INR Cr) | C11: ='35_Scenario_Analysis'!C7 -> 621614.38 | D11: ='35_Scenario_Analysis'!D7 -> 935375.79 | E11: ='35_Scenario_Analysis'!E7 -> 398296.65
B12: Net Cash / (Debt) (INR Cr) | C12: ='35_Scenario_Analysis'!C8 -> -137907.04 | D12: ='35_Scenario_Analysis'!D8 -> -137907.04 | E12: ='35_Scenario_Analysis'!E8 -> -137907.04
B13: Equity Value (INR Cr) | C13: ='35_Scenario_Analysis'!C9 -> 483707.34 | D13: ='35_Scenario_Analysis'!D9 -> 797468.76 | E13: ='35_Scenario_Analysis'!E9 -> 260389.62
B14: Diluted Shares | C14: ='35_Scenario_Analysis'!C10 -> 1257.9527 | D14: ='35_Scenario_Analysis'!D10 -> 1257.9527 | E14: ='35_Scenario_Analysis'!E10 -> 1257.9527
B15: Discount Rate (WACC %) | C15: ='35_Scenario_Analysis'!C11 -> 0.105567 | D15: ='35_Scenario_Analysis'!D11 -> 0.105567 | E15: ='35_Scenario_Analysis'!E11 -> 0.105567
B16: Terminal Growth Rate % | C16: ='35_Scenario_Analysis'!C12 -> 0.04 | D16: ='35_Scenario_Analysis'!D12 -> 0.04 | E16: ='35_Scenario_Analysis'!E12 -> 0.04
B17: FY31 Revenue (INR Cr) | C17: ='35_Scenario_Analysis'!C13 -> 622105.68 | D17: ='35_Scenario_Analysis'!D13 -> 792948.5 | E17: ='35_Scenario_Analysis'!E13 -> 482066.81
B18: FY31 EBITDA Margin % | C18: ='35_Scenario_Analysis'!C14 -> 0.179833 | D18: ='35_Scenario_Analysis'!D14 -> 0.204833 | E18: ='35_Scenario_Analysis'!E14 -> 0.154833

Sheet 03_Model_Control
B2: MODEL CONTROL & SCENARIO SELECTION
B3: Global Model Parameters and Active Scenario Toggles
B5: Control Parameter | C5: Current Value | D5: Description
B6: Active Scenario | C6: base | D6: Primary scenario driving live model sheets (base / bull / bear)
B7: Model Mode | C7: Analyst Mode | D7: Full financial modeling mode with 23 detail tabs
B8: Taxonomy Mapping | C8: INDIA Normalized Taxonomy v1.0 | D8: Normalized financial taxonomy registry
B9: Model Schema Version | C9: 1.0.0 | D9: Pydantic contract schema version
B10: Reporting Currency | C10: INR | D10: Company financial statement currency
B11: Display Unit Basis | C11: crores | D11: Monetary figures in INR Crores

Sheet 10_Income_Statement
B2: OIL & NATURAL GAS CORPORATION LIMITED — HISTORICAL INCOME STATEMENT
B3: Reporting Currency: INR | Units: crores
B5: Line Item | C5: FY24 | D5: FY25 | E5: FY26
B6: Revenue from Operations | C6: 598644.23 | D6: 608952.91 | E6: 605276.46
B7: Cost of Sales | C7: 458647.17 | D7: 480226.51 | E7: 458103.72
B8: Gross Profit | C8: 139997.07 | D8: 128726.41 | E8: 147172.74
B9: Employee Benefit Expense | C9: - | D9: - | E9: -
B10: Selling & Administrative Expense | C10: - | D10: - | E10: -
B11: Other Operating Expense | C11: - | D11: - | E11: -
B12: Operating Profit (EBIT) | C12: 77045.28 | D12: 63618.41 | E12: 81827.62
B13: Depreciation & Amortization | C13: 31514.93 | D13: 34692.8 | E13: 37262.54
B14: EBITDA | C14: 108560.21 | D14: 98311.21 | E14: 119090.17
B15: Other Income | C15: 5001.44 | D15: 5106.04 | E15: 5018.48
B16: Finance Cost / Interest Expense | C16: 11742.42 | D16: 12291.16 | E16: 10722.95
B17: Profit Before Tax (PBT) | C17: 73629.21 | D17: 52397.88 | E17: 67622.95
B18: Income Tax Expense | C18: 18356.07 | D18: 14069.27 | E18: 17829.84
B19: Net Profit After Tax | C19: 49143.93 | D19: 36225.62 | E19: 41424.38
B20: Basic EPS (INR) | C20: - | D20: - | E20: -
B21: Diluted EPS (INR) | C21: 39.06 | D21: 28.8 | E21: 32.93

Sheet 11_Balance_Sheet
B2: OIL & NATURAL GAS CORPORATION LIMITED — HISTORICAL BALANCE SHEET
B3: Reporting Currency: INR | Units: crores
B5: Line Item | C5: FY24 | D5: FY25 | E5: FY26
B6: Property, Plant & Equipment | C6: 422641.73 | D6: 439944.17 | E6: 448501.23
B7: Capital Work-in-Progress | C7: 25802.95 | D7: 23751.61 | E7: 13926.87
B8: Goodwill | C8: - | D8: - | E8: -
B9: Intangible Assets | C9: - | D9: - | E9: -
B10: Non-Current Investments | C10: - | D10: - | E10: -
B11: Deferred Tax Assets | C11: - | D11: - | E11: -
B12: Total Non-Current Assets | C12: - | D12: - | E12: -
B13: Trade Receivables | C13: 19704.13 | D13: 21227.8 | E13: 22014.48
B14: Unbilled Revenue | C14: - | D14: - | E14: -
B15: Cash & Cash Equivalents | C15: 45704.68 | D15: 30341.62 | E15: 36392.1
B16: Current Investments | C16: 41444.93 | D16: - | E16: -
B17: Total Current Assets | C17: - | D17: - | E17: -
B18: TOTAL ASSETS | C18: 741997.92 | D18: 758723.1 | E18: 791905.18
B19: Equity Share Capital | C19: 1258.03 | D19: 1258.03 | E19: 1258.03
B20: Total Equity / Net Worth | C20: - | D20: - | E20: -
B21: Trade Payables | C21: - | D21: - | E21: -
B22: TOTAL LIABILITIES & EQUITY | C22: 741997.92 | D22: 758723.1 | E22: 791905.18

Sheet 12_Cash_Flow
B2: OIL & NATURAL GAS CORPORATION LIMITED — HISTORICAL CASH FLOW STATEMENT
B3: Reporting Currency: INR | Units: crores
B5: Line Item | C5: FY24 | D5: FY25 | E5: FY26
B6: Net Cash from Operating Activities | C6: 98846.6 | D6: 90855.6 | E6: 112719.34
B7: Income Taxes Paid | C7: - | D7: - | E7: -
B8: Net Cash used in Investing Activities (Capex) | C8: -57485.02 | D8: -42999.04 | E8: -57675.86
B9: Business Acquisitions | C9: - | D9: - | E9: -
B10: Net Cash used in Financing Activities | C10: -45009.25 | D10: -47908.45 | E10: -56330.73
B11: Dividends Paid | C11: - | D11: - | E11: -
B12: NET CHANGE IN CASH & CASH EQUIVALENTS | C12: - | D12: - | E12: -

Sheet 13_Financial_Ratios
B2: OIL & NATURAL GAS CORPORATION LIMITED — HISTORICAL FINANCIAL RATIOS
B5: Metric / Ratio | C5: FY24 | D5: FY25 | E5: FY26
B6: Revenue YoY Growth % | C6: - | D6: 0.0172 | E6: -0.006
B7: EBITDA Margin % | C7: 0.1813 | D7: 0.1614 | E7: 0.1968
B8: Operating Margin (EBIT) % | C8: 0.1287 | D8: 0.1045 | E8: 0.1352
B9: Net Margin % | C9: 0.0821 | D9: 0.0595 | E9: 0.0684
B10: Effective Tax Rate % | C10: 0.2493 | D10: 0.2685 | E10: 0.2637
B11: Days Sales Outstanding (DSO) | C11: 12.0138 | D11: 12.7237 | E11: 13.2754
B12: Days Payables Outstanding (DPO) | C12: - | D12: - | E12: -
B13: D&A % Revenue | C13: 0.0526 | D13: 0.057 | E13: 0.0616

Sheet 14_Historical_Drivers
B2: OIL & NATURAL GAS CORPORATION LIMITED — HISTORICAL DRIVER INPUTS
B5: Driver Name | C5: FY24 | D5: FY25 | E5: FY26
B6: Revenue Growth Rate % | C6: - | D6: 0.0172 | E6: -0.006
B7: EBITDA Margin % | C7: 0.1813 | D7: 0.1614 | E7: 0.1968
B8: Operating Margin % | C8: 0.1287 | D8: 0.1045 | E8: 0.1352
B9: D&A % Revenue | C9: 0.0526 | D9: 0.057 | E9: 0.0616
B10: Effective Tax Rate % | C10: 0.2493 | D10: 0.2685 | E10: 0.2637
B11: DSO (Days) | C11: 12.0138 | D11: 12.7237 | E11: 13.2754
B12: DPO (Days) | C12: - | D12: - | E12: -
B13: Capex % Revenue | C13: 0.0871 | D13: 0.0914 | E13: 0.0892

Sheet 20_Operating_Model
B2: OIL & NATURAL GAS CORPORATION LIMITED — FORECAST OPERATING MODEL
B3: Scenario: Base Case | Reporting Currency: INR | Units: crores
B5: Line Item | C5: FY27 | D5: FY28 | E5: FY29 | F5: FY30 | G5: FY31
B6: Revenue from Operations | C6: ='21_Revenue_Build'!C7 -> 608605.48 | D6: ='21_Revenue_Build'!D7 -> 611952.81 | E6: ='21_Revenue_Build'!E7 -> 615318.55 | F6: ='21_Revenue_Build'!F7 -> 618702.8 | G6: ='21_Revenue_Build'!G7 -> 622105.67
B7: Cost of Sales | C7: =C6-C8 -> 460623.29 | D7: =D6-D8 -> 463156.71 | E7: =E6-E8 -> 465704.08 | F7: =F6-F8 -> 468265.45 | G7: =G6-G8 -> 470840.91
B8: Gross Profit | C8: 147982.19 | D8: 148796.1 | E8: 149614.47 | F8: 150437.35 | G8: 151264.76
B9: EBITDA | C9: ='22_Cost_Build'!C7 -> 109447.35 | D9: ='22_Cost_Build'!D7 -> 110049.31 | E9: ='22_Cost_Build'!E7 -> 110654.58 | F9: ='22_Cost_Build'!F7 -> 111263.18 | G9: ='22_Cost_Build'!G7 -> 111875.13
B10: Depreciation & Amortization | C10: ='24_Capex_D&A'!C9 -> 34731.29 | D10: ='24_Capex_D&A'!D9 -> 34922.31 | E10: ='24_Capex_D&A'!E9 -> 35114.38 | F10: ='24_Capex_D&A'!F9 -> 35307.51 | G10: ='24_Capex_D&A'!G9 -> 35501.7
B11: Operating Profit (EBIT) | C11: =C9-C10 -> 74736.75 | D11: =D9-D10 -> 75147.8 | E11: =E9-E10 -> 75561.12 | F11: =F9-F10 -> 75976.7 | G11: =G9-G10 -> 76394.58
B12: Other Income | C12: 5046.09 | D12: 5073.84 | E12: 5101.75 | F12: 5129.81 | G12: 5158.02
B13: Finance Cost | C13: ='25_Debt_Schedule'!C11 -> 10781.93 | D13: ='25_Debt_Schedule'!D11 -> 10841.23 | E13: ='25_Debt_Schedule'!E11 -> 10900.85 | F13: ='25_Debt_Schedule'!F11 -> 10960.81 | G13: ='25_Debt_Schedule'!G11 -> 11021.09
B14: Profit Before Tax (PBT) | C14: =C11+C12-C13 -> 69000.91 | D14: =D11+D12-D13 -> 69380.42 | E14: =E11+E12-E13 -> 69762.01 | F14: =F11+F12-F13 -> 70145.7 | G14: =G11+G12-G13 -> 70531.5
B15: Tax Expense | C15: =C14*'26_Tax_Schedule'!C6 -> 17974.74 | D15: =D14*'26_Tax_Schedule'!D6 -> 18073.6 | E15: =E14*'26_Tax_Schedule'!E6 -> 18019.53 | F15: =F14*'26_Tax_Schedule'!F6 -> 17964.31 | G15: =G14*'26_Tax_Schedule'!G6 -> 17907.95
B16: Net Profit After Tax | C16: =C14-C15 -> 51026.18 | D16: =D14-D15 -> 51306.82 | E16: =E14-E15 -> 51742.48 | F16: =F14-F15 -> 52181.39 | G16: =G14-G15 -> 52623.56
B17: Trade Receivables | C17: ='23_Working_Capital'!C7 -> 22176.58 | D17: ='23_Working_Capital'!D7 -> 22298.55 | E17: ='23_Working_Capital'!E7 -> 22421.2 | F17: ='23_Working_Capital'!F7 -> 22544.51 | G17: ='23_Working_Capital'!G7 -> 22668.51
B18: Trade Payables | C18: ='23_Working_Capital'!C9 -> 17667.74 | D18: ='23_Working_Capital'!D9 -> 17764.92 | E18: ='23_Working_Capital'!E9 -> 17862.62 | F18: ='23_Working_Capital'!F9 -> 17960.87 | G18: ='23_Working_Capital'!G9 -> 18059.65
B19: Cash & Cash Equivalents | C19: 64939.47 | D19: 78207.32 | E19: 94393.16 | F19: 112974.95 | G19: 133978.56
B20: Total Assets | C20: 840188.63 | D20: 871069.89 | E20: 902213.09 | F20: 933620.17 | G20: 965293.09
B21: Total Equity | C21: 30615.71 | D21: 61399.8 | E21: 92445.29 | F21: 123754.12 | G21: 155328.25
B22: Total Liabilities & Equity | C22: =C20 -> 840188.63 | D22: =D20 -> 871069.89 | E22: =E20 -> 902213.09 | F22: =F20 -> 933620.17 | G22: =G20 -> 965293.09
B23: Operating Cash Flow | C23: 103263.1 | D23: 86204.33 | E23: 86831.93 | F23: 87463.83 | G23: 88100.05
B24: Investing Cash Flow (Capex) | C24: ='24_Capex_D&A'!C7 -> -54305.26 | D24: ='24_Capex_D&A'!D7 -> -52413.76 | E24: ='24_Capex_D&A'!E7 -> -49949.1 | F24: ='24_Capex_D&A'!F7 -> -48009.48 | G24: ='24_Capex_D&A'!G7 -> -46047.02

Sheet 21_Revenue_Build
B2: REVENUE BUILD & YoY GROWTH FORECAST
B5: Segment / Driver | C5: FY27 | D5: FY28 | E5: FY29 | F5: FY30 | G5: FY31
B6: Assumed Revenue Growth Rate % | C6: 0.0055 | D6: 0.0055 | E6: 0.0055 | F6: 0.0055 | G6: 0.0055
B7: Consolidated Revenue (INR Cr) | C7: ='10_Income_Statement'!E6*(1+C6) -> 608605.48 | D7: =C7*(1+D6) -> 611952.81 | E7: =D7*(1+E6) -> 615318.55 | F7: =E7*(1+F6) -> 618702.8 | G7: =F7*(1+G6) -> 622105.67

Sheet 22_Cost_Build
B2: COST BUILD & MARGIN FORECAST
B5: Cost Component | C5: FY27 | D5: FY28 | E5: FY29 | F5: FY30 | G5: FY31
B6: EBITDA Margin % | C6: 0.179833 | D6: 0.179833 | E6: 0.179833 | F6: 0.179833 | G6: 0.179833
B7: EBITDA (INR Cr) | C7: ='21_Revenue_Build'!C7*C6 -> 109447.35 | D7: ='21_Revenue_Build'!D7*D6 -> 110049.31 | E7: ='21_Revenue_Build'!E7*E6 -> 110654.58 | F7: ='21_Revenue_Build'!F7*F6 -> 111263.18 | G7: ='21_Revenue_Build'!G7*G6 -> 111875.13
B8: Operating Profit Margin % | C8: 0.1228 | D8: 0.1228 | E8: 0.1228 | F8: 0.1228 | G8: 0.1228
B9: Operating Profit (INR Cr) | C9: ='21_Revenue_Build'!C7*C8 -> 74736.75 | D9: ='21_Revenue_Build'!D7*D8 -> 75147.8 | E9: ='21_Revenue_Build'!E7*E8 -> 75561.12 | F9: ='21_Revenue_Build'!F7*F8 -> 75976.7 | G9: ='21_Revenue_Build'!G7*G8 -> 76394.58

Sheet 23_Working_Capital
B2: WORKING CAPITAL FORECAST (DSO / DPO)
B5: Working Capital Driver | C5: FY27 | D5: FY28 | E5: FY29 | F5: FY30 | G5: FY31
B6: Days Sales Outstanding (DSO) | C6: 13.3 | D6: 13.3 | E6: 13.3 | F6: 13.3 | G6: 13.3
B7: Trade Receivables (INR Cr) | C7: ='21_Revenue_Build'!C7*C6/365 -> 22176.58 | D7: ='21_Revenue_Build'!D7*D6/365 -> 22298.55 | E7: ='21_Revenue_Build'!E7*E6/365 -> 22421.2 | F7: ='21_Revenue_Build'!F7*F6/365 -> 22544.51 | G7: ='21_Revenue_Build'!G7*G6/365 -> 22668.51
B8: Days Payables Outstanding (DPO) | C8: 14 | D8: 14 | E8: 14 | F8: 14 | G8: 14
B9: Trade Payables (INR Cr) | C9: ='20_Operating_Model'!C7*C8/365 -> 17667.74 | D9: ='20_Operating_Model'!D7*D8/365 -> 17764.92 | E9: ='20_Operating_Model'!E7*E8/365 -> 17862.62 | F9: ='20_Operating_Model'!F7*F8/365 -> 17960.87 | G9: ='20_Operating_Model'!G7*G8/365 -> 18059.65

Sheet 24_Capex_D&A
B2: CAPEX & DEPRECIATION SCHEDULE
B5: Capex & D&A Component | C5: FY27 | D5: FY28 | E5: FY29 | F5: FY30 | G5: FY31
B6: Capex % Revenue | C6: 0.089229 | D6: 0.08565 | E6: 0.081176 | F6: 0.077597 | G6: 0.074018
B7: Capex Outflow (INR Cr) | C7: =-'21_Revenue_Build'!C7*C6 -> -54305.26 | D7: =-'21_Revenue_Build'!D7*D6 -> -52413.76 | E7: =-'21_Revenue_Build'!E7*E6 -> -49949.1 | F7: =-'21_Revenue_Build'!F7*F6 -> -48009.48 | G7: =-'21_Revenue_Build'!G7*G6 -> -46047.02
B8: D&A % Revenue | C8: 0.057067 | D8: 0.057067 | E8: 0.057067 | F8: 0.057067 | G8: 0.057067
B9: D&A Expense (INR Cr) | C9: ='21_Revenue_Build'!C7*C8 -> 34731.29 | D9: ='21_Revenue_Build'!D7*D8 -> 34922.31 | E9: ='21_Revenue_Build'!E7*E8 -> 35114.38 | F9: ='21_Revenue_Build'!F7*F8 -> 35307.51 | G9: ='21_Revenue_Build'!G7*G8 -> 35501.7

Sheet 25_Debt_Schedule
B2: DEBT & BORROWINGS SCHEDULE (GENERIC)
B3: Oil & Natural Gas Corporation Limited — debt schedule from base scenario
B5: Debt Component | C5: FY27 | D5: FY28 | E5: FY29 | F5: FY30 | G5: FY31
B6: Opening Debt Balance (INR Cr) | C6: 174299.13 | D6: =C10 -> 174299.13 | E6: =D10 -> 174299.13 | F6: =E10 -> 174299.13 | G6: =F10 -> 174299.13
B7: Debt Drawdowns (INR Cr) | C7: 0 | D7: 0 | E7: 0 | F7: 0 | G7: 0
B8: Scheduled Repayments (INR Cr) | C8: 0 | D8: 0 | E8: 0 | F8: 0 | G8: 0
B9: Optional Repayments (INR Cr) | C9: 0 | D9: 0 | E9: 0 | F9: 0 | G9: 0
B10: Closing Debt Balance (INR Cr) | C10: =C6+C7-C8-C9 -> 174299.13 | D10: =D6+D7-D8-D9 -> 174299.13 | E10: =E6+E7-E8-E9 -> 174299.13 | F10: =F6+F7-F8-F9 -> 174299.13 | G10: =G6+G7-G8-G9 -> 174299.13
B11: Interest Expense (INR Cr) | C11: =AVERAGE(C6,C10)*'30_WACC'!C10 -> 13072.435 | D11: =AVERAGE(D6,D10)*'30_WACC'!C10 -> 13072.435 | E11: =AVERAGE(E6,E10)*'30_WACC'!C10 -> 13072.435 | F11: =AVERAGE(F6,F10)*'30_WACC'!C10 -> 13072.435 | G11: =AVERAGE(G6,G10)*'30_WACC'!C10 -> 13072.435

Sheet 26_Tax_Schedule
B2: EFFECTIVE TAX RATE SCHEDULE
B5: Tax Parameter | C5: FY27 | D5: FY28 | E5: FY29 | F5: FY30 | G5: FY31
B6: Effective Tax Rate % | C6: 0.2605 | D6: 0.2605 | E6: 0.2583 | F6: 0.2561 | G6: 0.2539
B7: PBT (INR Cr) | C7: ='20_Operating_Model'!C14 -> 69000.91 | D7: ='20_Operating_Model'!D14 -> 69380.42 | E7: ='20_Operating_Model'!E14 -> 69762.01 | F7: ='20_Operating_Model'!F14 -> 70145.7 | G7: ='20_Operating_Model'!G14 -> 70531.5
B8: Tax Expense (INR Cr) | C8: =C7*C6 -> 17974.74 | D8: =D7*D6 -> 18073.6 | E8: =E7*E6 -> 18019.53 | F8: =F7*F6 -> 17964.31 | G8: =G7*G6 -> 17907.95

Sheet 27_Share_Count
B2: DILUTED SHARE COUNT SCHEDULE
B5: Share Count Basis | C5: FY24 | D5: FY25 | E5: FY26 | F5: FY27 | G5: FY28 | H5: FY29 | I5: FY30 | J5: FY31
B6: Diluted Shares Outstanding (Cr) | C6: 1258.165 | D6: 1257.8341 | E6: 1257.9527 | F6: 1257.9527 | G6: 1257.9527 | H6: 1257.9527 | I6: 1257.9527 | J6: 1257.9527

Sheet 30_WACC
B2: WEIGHTED AVERAGE COST OF CAPITAL (WACC)
B3: CAPM Cost of Equity & Market Capital Weighting
B5: CAPM Component / Parameter | C5: Value | D5: Source / Provenance Notes
B6: Risk-Free Rate (Rf) % | C6: 0.0678 | D6: INDIA market default for rfr
B7: Equity Beta (β) | C7: 0.95 | D7: Per-company registry benchmark beta vs primary index
B8: Equity Risk Premium (ERP) % | C8: 0.0708 | D8: INDIA market default for erp
B9: Cost of Equity (r_e) % | C9: =C6+(C7*C8) -> 0.13506 | D9: CAPM formula: r_e = Rf + Beta * ERP
B10: Pre-Tax Cost of Debt % | C10: 0.075 | D10: ONGC pre-tax cost of borrowings
B11: Effective Tax Rate % | C11: 0.2605 | D11: Forecast average tax rate
B12: After-Tax Cost of Debt (r_d) % | C12: =C10*(1-C11) -> 0.0554625 | D12: Pre-tax * (1 - tax_rate)
B13: Equity Market Weight % | C13: 0.629473 | D13: Market Cap / Total Capital
B14: Debt Market Weight % | C14: 0.370527 | D14: Total Debt / Total Capital
B15: WEIGHTED AVERAGE COST OF CAPITAL (WACC) % | C15: =(C13*C9)+(C14*C12) -> 0.105567 | D15: Total WACC = Equity Weight * r_e + Debt Weight * r_d

Sheet 31_DCF
B2: OIL & NATURAL GAS CORPORATION LIMITED — DISCOUNTED CASH FLOW (DCF) MODEL
B3: 5-Year FCFF Build, PV Discounting & Enterprise Value Bridge
B5: FCFF Line Item / DCF Bridge | C5: FY27 | D5: FY28 | E5: FY29 | F5: FY30 | G5: FY31 | H5: Valuation Summary
B6: Operating Profit (EBIT) | C6: ='20_Operating_Model'!C11 -> 74736.75 | D6: ='20_Operating_Model'!D11 -> 75147.8 | E6: ='20_Operating_Model'!E11 -> 75561.12 | F6: ='20_Operating_Model'!F11 -> 75976.7 | G6: ='20_Operating_Model'!G11 -> 76394.58
B7: Effective Tax Rate % | C7: ='26_Tax_Schedule'!C6 -> 0.2605 | D7: ='26_Tax_Schedule'!D6 -> 0.2605 | E7: ='26_Tax_Schedule'!E6 -> 0.2583 | F7: ='26_Tax_Schedule'!F6 -> 0.2561 | G7: ='26_Tax_Schedule'!G6 -> 0.2539
B8: NOPAT (EBIT x (1 - Tax)) | C8: =C6*(1-C7) -> 55267.83 | D8: =D6*(1-D7) -> 55571.8 | E8: =E6*(1-E7) -> 56043.68 | F8: =F6*(1-F7) -> 56519.07 | G8: =G6*(1-G7) -> 56998
B9: Plus: D&A Expense | C9: ='20_Operating_Model'!C10 -> 34731.29 | D9: ='20_Operating_Model'!D10 -> 34922.31 | E9: ='20_Operating_Model'!E10 -> 35114.38 | F9: ='20_Operating_Model'!F10 -> 35307.51 | G9: ='20_Operating_Model'!G10 -> 35501.7
B10: Less: Capex Outflow | C10: =ABS('20_Operating_Model'!C24) -> 54305.26 | D10: =ABS('20_Operating_Model'!D24) -> 52413.76 | E10: =ABS('20_Operating_Model'!E24) -> 49949.1 | F10: =ABS('20_Operating_Model'!F24) -> 48009.48 | G10: =ABS('20_Operating_Model'!G24) -> 46047.02
B11: Less: Change in Working Capital | C11: =('23_Working_Capital'!C7-'23_Working_Capital'!C9)-('11_Balance_Sheet'!E10-'11_Balance_Sheet'!E17) -> -17505.64 | D11: =('23_Working_Capital'!D7-'23_Working_Capital'!D9)-('23_Working_Capital'!C7-'23_Working_Capital'!C9) -> 24.8 | E11: =('23_Working_Capital'!E7-'23_Working_Capital'!E9)-('23_Working_Capital'!D7-'23_Working_Capital'!D9) -> 24.94 | F11: =('23_Working_Capital'!F7-'23_Working_Capital'!F9)-('23_Working_Capital'!E7-'23_Working_Capital'!E9) -> 25.07 | G11: =('23_Working_Capital'!G7-'23_Working_Capital'!G9)-('23_Working_Capital'!F7-'23_Working_Capital'!F9) -> 25.21
B12: FREE CASH FLOW TO FIRM (FCFF) | C12: =C8+C9-C10-C11 -> 53199.5 | D12: =D8+D9-D10-D11 -> 38055.55 | E12: =E8+E9-E10-E11 -> 41184.02 | F12: =F8+F9-F10-F11 -> 43792.03 | G12: =G8+G9-G10-G11 -> 46427.47
B13: Mid-Year Discount Factor (1 / (1+WACC)^(t - 0.5)) | C13: =1/((1+'30_WACC'!C15)^(1-0.5)) -> 0.951059 | D13: =1/((1+'30_WACC'!C15)^(2-0.5)) -> 0.860245 | E13: =1/((1+'30_WACC'!C15)^(3-0.5)) -> 0.778103 | F13: =1/((1+'30_WACC'!C15)^(4-0.5)) -> 0.703805 | G13: =1/((1+'30_WACC'!C15)^(5-0.5)) -> 0.636601
B14: PRESENT VALUE OF FCFF | C14: =C12*C13 -> 50595.86 | D14: =D12*D13 -> 32737.11 | E14: =E12*E13 -> 32045.43 | F14: =F12*F13 -> 30821.04 | G14: =G12*G13 -> 29555.76
B16: DCF BRIDGE — EV TO EQUITY VALUE
B17: Cumulative PV of FCFF (Mid-Year) | H17: =SUM(C14:G14) -> 175755.2
B18: PV of Terminal Value | H18: ='32_Terminal_Value'!C13 -> 445859.18
B19: ENTERPRISE VALUE (EV) | H19: =H17+H18 -> 621614.38
B20: Plus: Cash & Cash Equivalents | H20: 36392.1
B21: Plus: Marketable Securities | H21: 0
B22: Plus: Non-Current Investments | H22: 0
B23: Less: Total Debt | H23: 174299.13
B24: Less: Minority Interest & Preferred | H24: 0
B25: Net Non-Operating Debt / (Cash) | H25: =(H23+H24)-(H20+H21+H22) -> 137907.04
B26: EQUITY VALUE | H26: =H19-H25 -> 483707.34
B27: Diluted Shares (Cr) | H27: ='27_Share_Count'!E6 -> 1257.9527
B28: IMPLIED SHARE PRICE (INR) | H28: =H26/H27 -> 384.52

Sheet 32_Terminal_Value
B2: TERMINAL VALUE CALCULATION (DUAL METHOD & QUALITY CHECKS)
B3: Gordon Perpetuity Growth, Exit Multiple & Terminal ROIC Analysis
B5: Terminal Value Parameter | C5: Value | D5: Methodology / Rule Notes
B6: Terminal Growth Rate % | C6: 0.04 | D6: Perpetuity growth rate (must be < WACC)
B7: FY31 Final Year FCFF (INR Cr) | C7: ='31_DCF'!G12 -> 46427.47 | D7: Final forecast year FCFF
B8: Gordon Growth Undiscounted TV | C8: =(C7*(1+C6)/('30_WACC'!C15-C6)) -> 736415.71 | D8: TV = FCFF_n * (1+g) / (WACC - g)
B9: Exit Multiple (EV/EBITDA) | C9: 20 | D9: Exit EV/EBITDA multiple
B10: FY31 Final Year EBITDA (INR Cr) | C10: ='20_Operating_Model'!G9 -> 111875.13 | D10: Final forecast year EBITDA
B11: Exit Multiple Undiscounted TV | C11: =C9*C10 -> 2237502.6 | D11: TV = EBITDA_n * Exit Multiple
B12: Discount Factor (t=5) | C12: =1/((1+'30_WACC'!C15)^5) -> 0.605445 | D12: Discount factor for Year 5
B13: DISCOUNTED TERMINAL VALUE (PV) | C13: =C8*C12 -> 445859.18 | D13: Gordon Growth PV of Terminal Value
B14: Terminal Year NOPAT (Quality Check) | C14: 59277.92 | D14: Terminal NOPAT = EBIT_5 * (1+g) * (1 - Tax)
B15: Implied Reinvestment Rate % | C15: 0.1855 | D15: Reinvestment Rate = (Terminal NOPAT - Terminal FCFF) / NOPAT
B16: Implied Terminal ROIC % | C16: 0.2157 | D16: ValueDriver check: g / Reinvestment Rate

Sheet 33_Sensitivity
B2: VALUATION SENSITIVITY ANALYSIS
B3: 2D Sensitivity Grids (WACC vs Terminal Growth & Exit Multiple)
B5: WACC % \ Growth % | C5: 0.03 | D5: 0.035 | E5: 0.04 | F5: 0.045 | G5: 0.05
B6: 0.0856 | C6: =((('31_DCF'!H17+('31_DCF'!G12*(1+C$5)/($B6-C$5))/(1+$B6)^5)-'31_DCF'!H25)/'31_DCF'!H27) -> 489.43 | D6: =((('31_DCF'!H17+('31_DCF'!G12*(1+D$5)/($B6-D$5))/(1+$B6)^5)-'31_DCF'!H25)/'31_DCF'!H27) -> 536.66 | E6: =((('31_DCF'!H17+('31_DCF'!G12*(1+E$5)/($B6-E$5))/(1+$B6)^5)-'31_DCF'!H25)/'31_DCF'!H27) -> 594.24 | F6: =((('31_DCF'!H17+('31_DCF'!G12*(1+F$5)/($B6-F$5))/(1+$B6)^5)-'31_DCF'!H25)/'31_DCF'!H27) -> 666 | G6: =((('31_DCF'!H17+('31_DCF'!G12*(1+G$5)/($B6-G$5))/(1+$B6)^5)-'31_DCF'!H25)/'31_DCF'!H27) -> 757.93
B7: 0.0956 | C7: =((('31_DCF'!H17+('31_DCF'!G12*(1+C$5)/($B7-C$5))/(1+$B7)^5)-'31_DCF'!H25)/'31_DCF'!H27) -> 400.07 | D7: =((('31_DCF'!H17+('31_DCF'!G12*(1+D$5)/($B7-D$5))/(1+$B7)^5)-'31_DCF'!H25)/'31_DCF'!H27) -> 432.29 | E7: =((('31_DCF'!H17+('31_DCF'!G12*(1+E$5)/($B7-E$5))/(1+$B7)^5)-'31_DCF'!H25)/'31_DCF'!H27) -> 470.31 | F7: =((('31_DCF'!H17+('31_DCF'!G12*(1+F$5)/($B7-F$5))/(1+$B7)^5)-'31_DCF'!H25)/'31_DCF'!H27) -> 515.83 | G7: =((('31_DCF'!H17+('31_DCF'!G12*(1+G$5)/($B7-G$5))/(1+$B7)^5)-'31_DCF'!H25)/'31_DCF'!H27) -> 571.34
B8: 0.1056 | C8: =((('31_DCF'!H17+('31_DCF'!G12*(1+C$5)/($B8-C$5))/(1+$B8)^5)-'31_DCF'!H25)/'31_DCF'!H27) -> 334.47 | D8: =((('31_DCF'!H17+('31_DCF'!G12*(1+D$5)/($B8-D$5))/(1+$B8)^5)-'31_DCF'!H25)/'31_DCF'!H27) -> 357.61 | E8: =((('31_DCF'!H17+('31_DCF'!G12*(1+E$5)/($B8-E$5))/(1+$B8)^5)-'31_DCF'!H25)/'31_DCF'!H27) -> 384.28 | F8: =((('31_DCF'!H17+('31_DCF'!G12*(1+F$5)/($B8-F$5))/(1+$B8)^5)-'31_DCF'!H25)/'31_DCF'!H27) -> 415.35 | G8: =((('31_DCF'!H17+('31_DCF'!G12*(1+G$5)/($B8-G$5))/(1+$B8)^5)-'31_DCF'!H25)/'31_DCF'!H27) -> 452
B9: 0.1156 | C9: =((('31_DCF'!H17+('31_DCF'!G12*(1+C$5)/($B9-C$5))/(1+$B9)^5)-'31_DCF'!H25)/'31_DCF'!H27) -> 284.29 | D9: =((('31_DCF'!H17+('31_DCF'!G12*(1+D$5)/($B9-D$5))/(1+$B9)^5)-'31_DCF'!H25)/'31_DCF'!H27) -> 301.56 | E9: =((('31_DCF'!H17+('31_DCF'!G12*(1+E$5)/($B9-E$5))/(1+$B9)^5)-'31_DCF'!H25)/'31_DCF'!H27) -> 321.11 | F9: =((('31_DCF'!H17+('31_DCF'!G12*(1+F$5)/($B9-F$5))/(1+$B9)^5)-'31_DCF'!H25)/'31_DCF'!H27) -> 343.43 | G9: =((('31_DCF'!H17+('31_DCF'!G12*(1+G$5)/($B9-G$5))/(1+$B9)^5)-'31_DCF'!H25)/'31_DCF'!H27) -> 369.15
B10: 0.1256 | C10: =((('31_DCF'!H17+('31_DCF'!G12*(1+C$5)/($B10-C$5))/(1+$B10)^5)-'31_DCF'!H25)/'31_DCF'!H27) -> 244.68 | D10: =((('31_DCF'!H17+('31_DCF'!G12*(1+D$5)/($B10-D$5))/(1+$B10)^5)-'31_DCF'!H25)/'31_DCF'!H27) -> 257.95 | E10: =((('31_DCF'!H17+('31_DCF'!G12*(1+E$5)/($B10-E$5))/(1+$B10)^5)-'31_DCF'!H25)/'31_DCF'!H27) -> 272.77 | F10: =((('31_DCF'!H17+('31_DCF'!G12*(1+F$5)/($B10-F$5))/(1+$B10)^5)-'31_DCF'!H25)/'31_DCF'!H27) -> 289.43 | G10: =((('31_DCF'!H17+('31_DCF'!G12*(1+G$5)/($B10-G$5))/(1+$B10)^5)-'31_DCF'!H25)/'31_DCF'!H27) -> 308.3
B13: WACC % \ Multiple | C13: 16 | D13: 18 | E13: 20 | F13: 22 | G13: 24
B14: 0.0856 | C14: =((('31_DCF'!H17+('20_Operating_Model'!G9*C$13)/(1+$B14)^5)-'31_DCF'!H25)/'31_DCF'!H27) -> 979.7 | D14: =((('31_DCF'!H17+('20_Operating_Model'!G9*D$13)/(1+$B14)^5)-'31_DCF'!H25)/'31_DCF'!H27) -> 1097.66 | E14: =((('31_DCF'!H17+('20_Operating_Model'!G9*E$13)/(1+$B14)^5)-'31_DCF'!H25)/'31_DCF'!H27) -> 1215.63 | F14: =((('31_DCF'!H17+('20_Operating_Model'!G9*F$13)/(1+$B14)^5)-'31_DCF'!H25)/'31_DCF'!H27) -> 1333.59 | G14: =((('31_DCF'!H17+('20_Operating_Model'!G9*G$13)/(1+$B14)^5)-'31_DCF'!H25)/'31_DCF'!H27) -> 1451.56
B15: 0.0956 | C15: =((('31_DCF'!H17+('20_Operating_Model'!G9*C$13)/(1+$B15)^5)-'31_DCF'!H25)/'31_DCF'!H27) -> 934.4 | D15: =((('31_DCF'!H17+('20_Operating_Model'!G9*D$13)/(1+$B15)^5)-'31_DCF'!H25)/'31_DCF'!H27) -> 1047.08 | E15: =((('31_DCF'!H17+('20_Operating_Model'!G9*E$13)/(1+$B15)^5)-'31_DCF'!H25)/'31_DCF'!H27) -> 1159.76 | F15: =((('31_DCF'!H17+('20_Operating_Model'!G9*F$13)/(1+$B15)^5)-'31_DCF'!H25)/'31_DCF'!H27) -> 1272.43 | G15: =((('31_DCF'!H17+('20_Operating_Model'!G9*G$13)/(1+$B15)^5)-'31_DCF'!H25)/'31_DCF'!H27) -> 1385.11
B16: 0.1056 | C16: =((('31_DCF'!H17+('20_Operating_Model'!G9*C$13)/(1+$B16)^5)-'31_DCF'!H25)/'31_DCF'!H27) -> 891.47 | D16: =((('31_DCF'!H17+('20_Operating_Model'!G9*D$13)/(1+$B16)^5)-'31_DCF'!H25)/'31_DCF'!H27) -> 999.14 | E16: =((('31_DCF'!H17+('20_Operating_Model'!G9*E$13)/(1+$B16)^5)-'31_DCF'!H25)/'31_DCF'!H27) -> 1106.81 | F16: =((('31_DCF'!H17+('20_Operating_Model'!G9*F$13)/(1+$B16)^5)-'31_DCF'!H25)/'31_DCF'!H27) -> 1214.49 | G16: =((('31_DCF'!H17+('20_Operating_Model'!G9*G$13)/(1+$B16)^5)-'31_DCF'!H25)/'31_DCF'!H27) -> 1322.16
B17: 0.1156 | C17: =((('31_DCF'!H17+('20_Operating_Model'!G9*C$13)/(1+$B17)^5)-'31_DCF'!H25)/'31_DCF'!H27) -> 850.76 | D17: =((('31_DCF'!H17+('20_Operating_Model'!G9*D$13)/(1+$B17)^5)-'31_DCF'!H25)/'31_DCF'!H27) -> 953.69 | E17: =((('31_DCF'!H17+('20_Operating_Model'!G9*E$13)/(1+$B17)^5)-'31_DCF'!H25)/'31_DCF'!H27) -> 1056.62 | F17: =((('31_DCF'!H17+('20_Operating_Model'!G9*F$13)/(1+$B17)^5)-'31_DCF'!H25)/'31_DCF'!H27) -> 1159.56 | G17: =((('31_DCF'!H17+('20_Operating_Model'!G9*G$13)/(1+$B17)^5)-'31_DCF'!H25)/'31_DCF'!H27) -> 1262.49
B18: 0.1256 | C18: =((('31_DCF'!H17+('20_Operating_Model'!G9*C$13)/(1+$B18)^5)-'31_DCF'!H25)/'31_DCF'!H27) -> 812.13 | D18: =((('31_DCF'!H17+('20_Operating_Model'!G9*D$13)/(1+$B18)^5)-'31_DCF'!H25)/'31_DCF'!H27) -> 910.58 | E18: =((('31_DCF'!H17+('20_Operating_Model'!G9*E$13)/(1+$B18)^5)-'31_DCF'!H25)/'31_DCF'!H27) -> 1009.02 | F18: =((('31_DCF'!H17+('20_Operating_Model'!G9*F$13)/(1+$B18)^5)-'31_DCF'!H25)/'31_DCF'!H27) -> 1107.46 | G18: =((('31_DCF'!H17+('20_Operating_Model'!G9*G$13)/(1+$B18)^5)-'31_DCF'!H25)/'31_DCF'!H27) -> 1205.9

Sheet 34_Reverse_DCF
B2: REVERSE DCF ANALYSIS
B3: Market Price Implied Perpetuity Growth Rate
B5: Reverse DCF Parameter | C5: Value | D5: Methodology Notes
B6: Current Market Benchmark Price (INR) | C6: 235.35 | D6: Market price input
B7: Market Implied Equity Value (INR Cr) | C7: =C6*'27_Share_Count'!E6 -> 296059.17 | D7: Market Price * Diluted Shares
B8: Market Implied EV (INR Cr) | C8: =C7+137907.04 -> 433966.21 | D8: Implied Equity Value + Net Debt
B9: Market Implied PV of TV (INR Cr) | C9: =C8-'31_DCF'!H17 -> 258211.01 | D9: Implied EV - Cumulative PV(FCFF)
B10: MARKET IMPLIED TERMINAL GROWTH % | C10: =((C9*(1+'30_WACC'!C15)^5*'30_WACC'!C15 - '31_DCF'!G12)/(C9*(1+'30_WACC'!C15)^5 + '31_DCF'!G12)) -> -0.002971 | D10: Solved exact implied perpetuity growth rate for market price INR 235.35

Sheet 35_Scenario_Analysis
B2: SCENARIO ANALYSIS COMPARISON
B3: Base, Bull, and Bear Scenarios Side-by-Side
B5: Valuation Metric / Driver | C5: Base Scenario | D5: Bull Scenario | E5: Bear Scenario
B6: Implied Share Price (INR) | C6: 384.52 | D6: 633.94 | E6: 206.99
B7: Enterprise Value (INR Cr) | C7: 621614.38 | D7: 935375.79 | E7: 398296.65
B8: Net Cash / (Debt) (INR Cr) | C8: -137907.04 | D8: -137907.04 | E8: -137907.04
B9: Equity Value (INR Cr) | C9: 483707.34 | D9: 797468.76 | E9: 260389.62
B10: Diluted Shares | C10: 1257.9527 | D10: 1257.9527 | E10: 1257.9527
B11: Discount Rate (WACC %) | C11: 0.105567 | D11: 0.105567 | E11: 0.105567
B12: Terminal Growth Rate % | C12: 0.04 | D12: 0.04 | E12: 0.04
B13: FY31 Revenue (INR Cr) | C13: 622105.68 | D13: 792948.5 | E13: 482066.81
B14: FY31 EBITDA Margin % | C14: 0.179833 | D14: 0.204833 | E14: 0.154833

Sheet 50_Data_Sources
B2: DATA SOURCES & PROVENANCE METADATA
B5: Canonical Key / Line Item | C5: Period | D5: Status | E5: Source / Derivation Lineage
B6: canonical.is.revenue | C6: FY24-FY26 | D6: Reported | E6: Oil & Natural Gas Corporation Limited Audited Financial Statements (INDIA regulatory filing)
B7: canonical.is.cost_of_sales | C7: FY24-FY26 | D7: Reported | E7: Oil & Natural Gas Corporation Limited Audited Financial Statements (INDIA regulatory filing)
B8: canonical.is.ebitda | C8: FY24-FY26 | D8: Derived | E8: Derived formula: Operating Profit + Depreciation & Amortization
B9: canonical.bs.cash_and_bank | C9: FY24-FY26 | D9: Reported | E9: Oil & Natural Gas Corporation Limited Consolidated Balance Sheet
B10: canonical.bs.total_assets | C10: FY24-FY26 | D10: Reported | E10: Oil & Natural Gas Corporation Limited Consolidated Balance Sheet
B11: canonical.cf.operating_activities | C11: FY24-FY26 | D11: Reported | E11: Oil & Natural Gas Corporation Limited Consolidated Cash Flow Statement

Sheet 51_Assumption_Log
B2: ASSUMPTION AUDIT LOG
B5: Driver Key | C5: Period | D5: Scenario | E5: Value | F5: Type | G5: Source / Provenance Method
B6: revenue_growth | C6: FY27 | D6: base | E6: 0.55 | F6: model_generated | G6: CAGR (FY24-FY26: 0.6%) faded by factor 1.00
B7: revenue_growth | C7: FY28 | D7: base | E7: 0.55 | F7: model_generated | G7: CAGR (FY24-FY26: 0.6%) faded by factor 1.00
B8: revenue_growth | C8: FY29 | D8: base | E8: 0.55 | F8: model_generated | G8: CAGR (FY24-FY26: 0.6%) faded by factor 1.00
B9: revenue_growth | C9: FY30 | D9: base | E9: 0.55 | F9: model_generated | G9: CAGR (FY24-FY26: 0.6%) faded by factor 1.00
B10: revenue_growth | C10: FY31 | D10: base | E10: 0.55 | F10: model_generated | G10: CAGR (FY24-FY26: 0.6%) faded by factor 1.00
B11: ebitda_margin | C11: FY27 | D11: base | E11: 17.9833 | F11: model_generated | G11: Multi-year average EBITDA margin (FY24-FY26)
B12: ebitda_margin | C12: FY28 | D12: base | E12: 17.9833 | F12: model_generated | G12: Multi-year average EBITDA margin (FY24-FY26)
B13: ebitda_margin | C13: FY29 | D13: base | E13: 17.9833 | F13: model_generated | G13: Multi-year average EBITDA margin (FY24-FY26)
B14: ebitda_margin | C14: FY30 | D14: base | E14: 17.9833 | F14: model_generated | G14: Multi-year average EBITDA margin (FY24-FY26)
B15: ebitda_margin | C15: FY31 | D15: base | E15: 17.9833 | F15: model_generated | G15: Multi-year average EBITDA margin (FY24-FY26)
B16: ebit_margin | C16: FY27 | D16: base | E16: 12.28 | F16: model_generated | G16: Multi-year average operating margin (FY24-FY26)
B17: ebit_margin | C17: FY28 | D17: base | E17: 12.28 | F17: model_generated | G17: Multi-year average operating margin (FY24-FY26)
... B59: exit_ev_multiple | C59: terminal | D59: base | E59: 20 | F59: model_generated | G59: structural placeholder

Sheet 52_Model_Checks
B2: QA / MODEL CHECKS AUDIT ROLLUP
B3: Overall Status: MODEL VALID
B5: Check Name | C5: Category | D5: Result | E5: Detail / Failure Reason
B6: balance_sheet_balances | C6: accounting | D6: =IF(ABS('11_Balance_Sheet'!E14-'11_Balance_Sheet'!E22)<1.0,"PASS","FAIL") -> PASS | E6: Verified OK
B7: cash_flow_reconciles | C7: accounting | D7: =IF(ABS('12_Cash_Flow'!E12-('11_Balance_Sheet'!E11-'11_Balance_Sheet'!D11))<1.0,"PASS","FAIL") -> PASS | E7: Verified OK
B8: debt_schedule_reconciles | C8: accounting | D8: =IF(ABS('25_Debt_Schedule'!C10-'11_Balance_Sheet'!E16)<1.0,"PASS","FAIL") -> PASS | E8: Verified OK
B9: share_count_consistent | C9: accounting | D9: =IF('27_Share_Count'!E6>0,"PASS","FAIL") -> PASS | E9: Verified OK
B10: dcf_bridge_reconciles | C10: valuation | D10: =IF(ABS('31_DCF'!H19-('31_DCF'!H17+'31_DCF'!H18))<1.0,"PASS","FAIL") -> PASS | E10: Verified OK
B11: wacc_valid | C11: valuation | D11: =IF(AND('30_WACC'!C15>0.03,'30_WACC'!C15<0.30),"PASS","FAIL") -> PASS | E11: Verified OK
B12: terminal_growth_lt_wacc | C12: valuation | D12: =IF('32_Terminal_Value'!C6<'30_WACC'!C15,"PASS","FAIL") -> PASS | E12: Verified OK
B13: no_missing_critical_inputs | C13: data_quality | D13: =IF('31_DCF'!H28>0,"PASS","FAIL") -> PASS | E13: Verified OK
B14: data_provenance_quality | C14: data_quality | D14: =IF(COUNTA('50_Data_Sources'!B6:B11)>0,"PASS","FAIL") -> PASS | E14: Verified OK

Sheet 53_Methodology
B2: SYSTEM METHODOLOGY DOCUMENTATION
B5: Methodology Section | C5: Description / Formula Rules
B6: Normalization & Derivation | C6: Canonical keys map raw reported labels. Derived EBITDA = EBIT + D&A.
B7: Driver Engine | C7: Forecast drivers apply to prior period actuals. Revenue = Rev_(t-1) * (1 + g).
B8: Working Capital | C8: Receivables = Revenue * DSO / 365. Payables = Cost of Sales * DPO / 365.
B9: Balance Sheet Closure | C9: Total Assets = Prior Assets + Capex - D&A + Delta_WC. Cash is the balancing plug.
B10: Valuation Engine | C10: CAPM Cost of Equity = Rfr + Beta * ERP. WACC = Eq_Weight * r_e + Debt_Weight * r_d.
B11: Terminal Value | C11: Gordon Growth TV = FCFF_n * (1+g) / (WACC - g). Exit Multiple TV = EBITDA_n * Multiple.
B12: DCF Bridge | C12: EV = Sum PV(FCFF) + PV(TV). Equity Value = EV - Net Debt. Implied Price = Equity Value / Shares.
